fitmulticell/C.py
fitmulticell/__init__.py
fitmulticell/log.py
fitmulticell/version.py
fitmulticell/PEtab/__init__.py
fitmulticell/PEtab/base.py
fitmulticell/data/__init__.py
fitmulticell/distance/__init__.py
fitmulticell/distance/distribution.py
fitmulticell/model/__init__.py
fitmulticell/model/base.py
fitmulticell/sumstat/__init__.py
fitmulticell/sumstat/base.py
fitmulticell/sumstat/cell_types_cout.py
fitmulticell/sumstat/hexagonal_cluster_sumstat.py
fitmulticell/sumstat/plot_sumstat.py
fitmulticell/util/__init__.py
fitmulticell/util/base.py
test/__init__.py
test/test_PEtab.py
test/test_healty_fitting.py
test/test_log.py
test/test_parameter.py
test/test_simulation.py
test/test_sumstat.py
fitmulticell-0.0.9.dist-info/LICENSE.txt
fitmulticell-0.0.9.dist-info/METADATA
fitmulticell-0.0.9.dist-info/WHEEL
fitmulticell-0.0.9.dist-info/top_level.txt
fitmulticell-0.0.9.dist-info/RECORD
