Metadata-Version: 2.1
Name: fitmulticell
Version: 0.0.9
Summary: Fit multi-cellular and multi-scale models
Home-page: https://gitlab.com/fitmulticell/fit
Author: The FitMultiCell developers
Author-email: emad.alamoudi@uni-bonn.de
Maintainer: Emad Alamoudi
Maintainer-email: emad.alamoudi@uni-bonn.de
License: BSD-3-Clause
Download-URL: https://gitlab.com/fitmulticell/fit/-/releases
Project-URL: Bug Tracker, https://gitlab.com/fitmulticell/fit/-/issues
Project-URL: Documentation, https://fitmulticell.readthedocs.io
Project-URL: Changelog, https://fitmulticell.readthedocs.io/en/latest/changelog.html
Keywords: multi-cellular,multi-scale,abc,approximate bayesian computation,inference,pyabc,morpheus
Platform: UNKNOWN
Classifier: Development Status :: 3 - Alpha
Classifier: License :: OSI Approved :: BSD License
Classifier: Operating System :: OS Independent
Classifier: Programming Language :: Python
Classifier: Programming Language :: Python :: 3.10
Classifier: Programming Language :: Python :: 3.9
Classifier: Programming Language :: Python :: 3.8
Classifier: Programming Language :: Python :: 3.7
Requires-Python: >=3.7
Requires-Dist: numpy (>=1.19.1)
Requires-Dist: scipy (>=1.5.2)
Requires-Dist: pandas (>=1.2.0)
Requires-Dist: matplotlib (>=3.3.0)
Requires-Dist: pyabc (>=0.11.9)
Requires-Dist: petab-MS (>=0.1.20)
Requires-Dist: tidynamics (>=1.0.0)
Provides-Extra: doc
Requires-Dist: sphinx (>=3.1.0) ; extra == 'doc'
Requires-Dist: nbsphinx (>=0.7.0) ; extra == 'doc'
Requires-Dist: nbconvert (>=5.6.1) ; extra == 'doc'
Requires-Dist: sphinx-rtd-theme (>=0.4.3) ; extra == 'doc'
Requires-Dist: sphinx-autodoc-typehints (>=1.11.1) ; extra == 'doc'
Requires-Dist: ipython (>=7.18.1) ; extra == 'doc'
Provides-Extra: test
Requires-Dist: pytest (>=5.4.3) ; extra == 'test'
Requires-Dist: pytest-cov (>=2.10.0) ; extra == 'test'
Requires-Dist: pytest-rerunfailures (>=9.1.1) ; extra == 'test'
